stgrid2area/__init__.py
stgrid2area/__version__.py
stgrid2area/area.py
stgrid2area/processor.py
stgrid2area/util.py
stgrid2area-0.1.1.dist-info/licenses/LICENSE
stgrid2area-0.1.1.dist-info/METADATA
stgrid2area-0.1.1.dist-info/WHEEL
stgrid2area-0.1.1.dist-info/top_level.txt
stgrid2area-0.1.1.dist-info/RECORD
