Metadata-Version: 2.4
Name: stgrid2area
Version: 0.1.1
Summary: Extract and aggregate spatio-temporal data to a specified area.
Author: Alexander Dolich
Author-email: alexander.dolich@kit.edu
License: CC0-1.0 license
License-File: LICENSE
Requires-Dist: geopandas
Requires-Dist: pandas
Requires-Dist: xarray[io]
Requires-Dist: rioxarray
Requires-Dist: exactextract
Requires-Dist: dask[distributed]
Requires-Dist: dask_mpi
Requires-Dist: bokeh
Dynamic: author
Dynamic: author-email
Dynamic: description
Dynamic: description-content-type
Dynamic: license
Dynamic: license-file
Dynamic: requires-dist
Dynamic: summary
